CHANGES.txt
LICENSE.txt
MANIFEST.in
README.txt
files.txt
setup.py
LipidConverter.egg-info/PKG-INFO
LipidConverter.egg-info/SOURCES.txt
LipidConverter.egg-info/dependency_links.txt
LipidConverter.egg-info/requires.txt
LipidConverter.egg-info/top_level.txt
bin/lipid_converter.py
docs/usage.txt
lipid_conv/__init__.py
lipid_conv/aux.py
lipid_conv/convert.py
lipid_conv/forcefields.py
lipid_conv/lipid_conv.py
lipid_conv/structure.py
lipid_conv/transform.py
lipid_conv/berger/conversions.top
lipid_conv/berger/sortings.top
lipid_conv/berger/transforms.top
lipid_conv/charmm36/conversions.top
lipid_conv/charmm36/sortings.top
lipid_conv/charmm36/transforms.top
lipid_conv/gromos43a1-S3/conversions.top
lipid_conv/gromos43a1-S3/sortings.top
lipid_conv/gromos43a1-S3/transforms.top
lipid_conv/gromos53a6/sortings.top
lipid_conv/gromos53a6/transforms.top
lipid_conv/gromos54a7/sortings.top
lipid_conv/gromos54a7/transforms.top
lipid_conv/lipid11/sortings.top
lipid_conv/lipid11/transforms.top
lipid_conv/opls/sortings.top
lipid_conv/opls/transforms.top