Metadata-Version: 1.0
Name: LipidConverter
Version: 0.1.4
Summary: Useful descripton text
Home-page: http://lipid-converter.appspot.com
Author: Per Larsson
Author-email: larsson.r.per@gmail.com
License: LICENSE.txt
Platform: UNKNOWN
